{"cameraMode":{"drawMode":0,"name":"Shaded","section":"Shading Mode"},"sceneLighting":true,"audioPlay":false,"sceneViewState":{"m_AlwaysRefresh":false,"showFog":true,"showSkybox":true,"showFlares":true,"showImageEffects":true,"showParticleSystems":true,"showVisualEffectGraphs":true,"m_FxEnabled":true},"in2DMode":false,"pivot":{"x":203.11839294433595,"y":193.77113342285157,"z":-373.2304992675781},"rotation":{"x":-0.13480499386787415,"y":0.036254484206438068,"z":-0.004928864538669586,"w":-0.9901744723320007},"size":6.977488040924072,"orthographic":false}